app.py
data.py
flask_blog_app-0.1.6.dist-info/METADATA
flask_blog_app-0.1.6.dist-info/WHEEL
flask_blog_app-0.1.6.dist-info/top_level.txt
flask_blog_app-0.1.6.dist-info/RECORD
