Metadata-Version: 2.4
Name: flask-blog-app
Version: 0.1.6
Summary: A simple Flask blog application.
Author: Gruppo I Processati
Classifier: Programming Language :: Python :: 3
Classifier: License :: OSI Approved :: MIT License
Classifier: Operating System :: OS Independent
Classifier: Framework :: Flask
Requires-Python: >=3.11
Requires-Dist: Flask
Requires-Dist: flask-mysqldb
Requires-Dist: WTForms
Requires-Dist: passlib
Requires-Dist: gunicorn
Dynamic: author
Dynamic: classifier
Dynamic: requires-dist
Dynamic: requires-python
Dynamic: summary
